herre/__init__.py
herre/builders.py
herre/errors.py
herre/fakts/__init__.py
herre/fakts/fakts_endpoint_fetcher.py
herre/fakts/fakts_qt_store.py
herre/fakts/grant.py
herre/fakts/registry.py
herre/fetcher/__init__.py
herre/fetcher/errors.py
herre/fetcher/models.py
herre/fetcher/userinfo_fetcher.py
herre/grants/__init__.py
herre/grants/auto_login.py
herre/grants/base.py
herre/grants/errors.py
herre/grants/meta/__init__.py
herre/grants/meta/cache.py
herre/grants/oauth2/__init__.py
herre/grants/oauth2/authorization_code.py
herre/grants/oauth2/base.py
herre/grants/oauth2/client_credentials.py
herre/grants/oauth2/errors.py
herre/grants/oauth2/redirecters/__init__.py
herre/grants/oauth2/redirecters/aiohttp_server.py
herre/grants/oauth2/redirecters/mock.py
herre/grants/oauth2/redirecters/qt_login_view.py
herre/grants/oauth2/refresh.py
herre/grants/oauth2/utils.py
herre/grants/qt/auto_login.py
herre/grants/qt/errors.py
herre/grants/qt/settings_store.py
herre/grants/static.py
herre/herre.py
herre/models.py
herre-1.0.0.dist-info/METADATA
herre-1.0.0.dist-info/WHEEL
herre-1.0.0.dist-info/RECORD
