Metadata-Version: 2.1
Name: herre
Version: 1.0.0
Summary: oauth2/openid client tailored to pyqt and async environments
License: CC BY-NC 3.0
Author: jhnnsrs
Author-email: jhnnsrs@gmail.com
Requires-Python: >=3.8,<4.0
Classifier: License :: Other/Proprietary License
Classifier: Programming Language :: Python :: 3
Classifier: Programming Language :: Python :: 3.8
Classifier: Programming Language :: Python :: 3.9
Classifier: Programming Language :: Python :: 3.10
Classifier: Programming Language :: Python :: 3.11
Classifier: Programming Language :: Python :: 3.12
Provides-Extra: qt
Provides-Extra: windowed
Requires-Dist: QtPy (>=2.0.1,<3.0.0) ; extra == "qt"
Requires-Dist: aiohttp (>3.7.4)
Requires-Dist: certifi (>2021)
Requires-Dist: koil (>=1.0.0)
Requires-Dist: oauthlib (>=3.1.1,<4.0.0)
Requires-Dist: pydantic (>2)
